freezerbox/__init__.py
freezerbox/byoc.py
freezerbox/conf.toml
freezerbox/config.py
freezerbox/errors.py
freezerbox/fields.py
freezerbox/model.py
freezerbox/utils.py
freezerbox/cli/__init__.py
freezerbox/cli/main.py
freezerbox/group_by/__init__.py
freezerbox/group_by/attr.py
freezerbox/group_by/dependency.py
freezerbox/loaders/__init__.py
freezerbox/loaders/excel.py
freezerbox/stepwise/__init__.py
freezerbox/stepwise/dilute.py
freezerbox/stepwise/make.py
freezerbox-0.26.0.dist-info/entry_points.txt
freezerbox-0.26.0.dist-info/LICENSE.txt
freezerbox-0.26.0.dist-info/WHEEL
freezerbox-0.26.0.dist-info/METADATA
freezerbox-0.26.0.dist-info/RECORD
