Metadata-Version: 2.1
Name: freezerbox
Version: 0.26.0
Summary: Database of DNA sequences.
Author-email: Kale Kundert <kale@thekunderts.net>
Requires-Python: ~=3.8
Classifier: Programming Language :: Python :: 3
Classifier: License :: OSI Approved :: MIT License
Requires-Dist: byoc
Requires-Dist: autoprop
Requires-Dist: autosnapgene
Requires-Dist: biopython
Requires-Dist: docopt
Requires-Dist: entrypoints
Requires-Dist: exmemo
Requires-Dist: inform~=1.21
Requires-Dist: mako
Requires-Dist: mergedeep
Requires-Dist: more_itertools~=8.0
Requires-Dist: natsort
Requires-Dist: networkx
Requires-Dist: numpy
Requires-Dist: pandas
Requires-Dist: parsy
Requires-Dist: rtoml
Requires-Dist: sklearn
Requires-Dist: stepwise~=0.23
Requires-Dist: stringcase
Requires-Dist: tidyexc
Requires-Dist: tqdm
Requires-Dist: voluptuous
Requires-Dist: sphinx ; extra == "doc"
Requires-Dist: sphinx_rtd_theme ; extra == "doc"
Requires-Dist: autoclasstoc ; extra == "doc"
Requires-Dist: pytest ; extra == "test"
Requires-Dist: pytest-cov ; extra == "test"
Requires-Dist: coveralls ; extra == "test"
Requires-Dist: parametrize_from_file ; extra == "test"
Requires-Dist: pytest_tmp_files ; extra == "test"
Requires-Dist: re_assert ; extra == "test"
Project-URL: Bug Tracker, https://github.com/kalekundert/freezerbox/issues
Project-URL: Continuous Integration, https://github.com/kalekundert/freezerbox/actions
Project-URL: Documentation, https://freezerbox.readthedocs.io/en/latest/
Project-URL: Test Coverage, https://coveralls.io/github/kalekundert/freezerbox
Project-URL: Version Control, https://github.com/kalekundert/freezerbox
Provides-Extra: doc
Provides-Extra: test
